django_better_azure_communication_email/__init__.py
django_better_azure_communication_email/attachment.py
django_better_azure_communication_email/backend.py
django_better_azure_communication_email/settings.py
django_better_azure_communication_email/utils.py
django_better_azure_communication_email-0.0.1.dist-info/LICENSE
django_better_azure_communication_email-0.0.1.dist-info/METADATA
django_better_azure_communication_email-0.0.1.dist-info/WHEEL
django_better_azure_communication_email-0.0.1.dist-info/RECORD
