Metadata-Version: 2.1
Name: django-better-azure-communication-email
Version: 0.0.1
Summary: A better Django email backend for Azure Communication Email service.
Home-page: https://github.com/itm8-CDC/django-better-azure-communication-email
License: Apache-2.0
Keywords: django,email,azure
Author: Frederich Pedersen
Author-email: frodo@hobbits.dk
Requires-Python: >=3.8,<4.0
Classifier: Development Status :: 5 - Production/Stable
Classifier: Framework :: Django
Classifier: Framework :: Django :: 4.2
Classifier: Framework :: Django :: 5.0
Classifier: Framework :: Django :: 5.1
Classifier: Intended Audience :: Developers
Classifier: License :: OSI Approved :: Apache Software License
Classifier: Operating System :: OS Independent
Classifier: Programming Language :: Python
Classifier: Programming Language :: Python :: 3
Classifier: Programming Language :: Python :: 3.8
Classifier: Programming Language :: Python :: 3.9
Classifier: Programming Language :: Python :: 3.10
Classifier: Programming Language :: Python :: 3.11
Classifier: Programming Language :: Python :: 3.12
Classifier: Programming Language :: Python :: 3.13
Classifier: Topic :: Software Development :: Libraries :: Python Modules
Requires-Dist: azure-communication-email (>=1.0)
Requires-Dist: azure-identity (>=1.15)
Project-URL: Bug Tracker, https://github.com/itm8-CDC/django-better-azure-communication-email/issues
Project-URL: Company Website, https://itm8.com/
Project-URL: Repository, https://github.com/itm8-CDC/django-better-azure-communication-email
